{
 "custom_fields": [
  {
   "_assign": null,
   "_comments": null,
   "_liked_by": null,
   "_user_tags": null,
   "allow_in_quick_entry": 0,
   "allow_on_submit": 0,
   "bold": 0,
   "collapsible": 0,
   "collapsible_depends_on": null,
   "columns": 0,
   "creation": "2024-09-26 17:24:59.129184",
   "default": null,
   "depends_on": null,
   "description": null,
   "docstatus": 0,
   "dt": "Task",
   "fetch_from": "project.custom_product",
   "fetch_if_empty": 0,
   "fieldname": "custom_product",
   "fieldtype": "Link",
   "hidden": 0,
   "hide_border": 0,
   "hide_days": 0,
   "hide_seconds": 0,
   "idx": 5,
   "ignore_user_permissions": 0,
   "ignore_xss_filter": 0,
   "in_global_search": 0,
   "in_list_view": 0,
   "in_preview": 0,
   "in_standard_filter": 0,
   "insert_after": "custom_subservice_area",
   "is_system_generated": 0,
   "is_virtual": 0,
   "label": "Product",
   "length": 0,
   "mandatory_depends_on": null,
   "modified": "2024-09-26 17:24:59.129184",
   "modified_by": "Administrator",
   "module": null,
   "name": "Task-custom_product",
   "no_copy": 0,
   "non_negative": 0,
   "options": "Product",
   "owner": "Administrator",
   "permlevel": 0,
   "precision": "",
   "print_hide": 0,
   "print_hide_if_no_value": 0,
   "print_width": null,
   "read_only": 1,
   "read_only_depends_on": null,
   "report_hide": 0,
   "reqd": 0,
   "search_index": 0,
   "show_dashboard": 0,
   "sort_options": 0,
   "translatable": 0,
   "unique": 0,
   "width": null
  },
  {
   "_assign": null,
   "_comments": null,
   "_liked_by": null,
   "_user_tags": null,
   "allow_in_quick_entry": 0,
   "allow_on_submit": 0,
   "bold": 0,
   "collapsible": 0,
   "collapsible_depends_on": null,
   "columns": 0,
   "creation": "2024-09-26 17:24:58.759405",
   "default": null,
   "depends_on": null,
   "description": null,
   "docstatus": 0,
   "dt": "Task",
   "fetch_from": "project.custom_subservice_area",
   "fetch_if_empty": 0,
   "fieldname": "custom_subservice_area",
   "fieldtype": "Link",
   "hidden": 0,
   "hide_border": 0,
   "hide_days": 0,
   "hide_seconds": 0,
   "idx": 4,
   "ignore_user_permissions": 0,
   "ignore_xss_filter": 0,
   "in_global_search": 0,
   "in_list_view": 0,
   "in_preview": 0,
   "in_standard_filter": 0,
   "insert_after": "custom_program",
   "is_system_generated": 0,
   "is_virtual": 0,
   "label": "Subservice Area",
   "length": 0,
   "mandatory_depends_on": null,
   "modified": "2024-09-26 17:24:58.759405",
   "modified_by": "Administrator",
   "module": null,
   "name": "Task-custom_subservice_area",
   "no_copy": 0,
   "non_negative": 0,
   "options": "Subservice Area",
   "owner": "Administrator",
   "permlevel": 0,
   "precision": "",
   "print_hide": 0,
   "print_hide_if_no_value": 0,
   "print_width": null,
   "read_only": 1,
   "read_only_depends_on": null,
   "report_hide": 0,
   "reqd": 0,
   "search_index": 0,
   "show_dashboard": 0,
   "sort_options": 0,
   "translatable": 0,
   "unique": 0,
   "width": null
  },
  {
   "_assign": null,
   "_comments": null,
   "_liked_by": null,
   "_user_tags": null,
   "allow_in_quick_entry": 0,
   "allow_on_submit": 0,
   "bold": 0,
   "collapsible": 0,
   "collapsible_depends_on": null,
   "columns": 0,
   "creation": "2024-09-25 16:22:54.195860",
   "default": null,
   "depends_on": null,
   "description": null,
   "docstatus": 0,
   "dt": "Task",
   "fetch_from": "project.custom_program",
   "fetch_if_empty": 0,
   "fieldname": "custom_program",
   "fieldtype": "Link",
   "hidden": 0,
   "hide_border": 0,
   "hide_days": 0,
   "hide_seconds": 0,
   "idx": 3,
   "ignore_user_permissions": 0,
   "ignore_xss_filter": 0,
   "in_global_search": 0,
   "in_list_view": 0,
   "in_preview": 0,
   "in_standard_filter": 0,
   "insert_after": "project",
   "is_system_generated": 0,
   "is_virtual": 0,
   "label": "Program",
   "length": 0,
   "mandatory_depends_on": null,
   "modified": "2024-09-25 16:22:54.195860",
   "modified_by": "Administrator",
   "module": null,
   "name": "Task-custom_program",
   "no_copy": 0,
   "non_negative": 0,
   "options": "Program",
   "owner": "Administrator",
   "permlevel": 0,
   "precision": "",
   "print_hide": 0,
   "print_hide_if_no_value": 0,
   "print_width": null,
   "read_only": 1,
   "read_only_depends_on": null,
   "report_hide": 0,
   "reqd": 0,
   "search_index": 0,
   "show_dashboard": 0,
   "sort_options": 0,
   "translatable": 0,
   "unique": 0,
   "width": null
  },
  {
   "_assign": null,
   "_comments": null,
   "_liked_by": null,
   "_user_tags": null,
   "allow_in_quick_entry": 0,
   "allow_on_submit": 0,
   "bold": 0,
   "collapsible": 0,
   "collapsible_depends_on": null,
   "columns": 0,
   "creation": "2024-05-13 20:26:29.523226",
   "default": null,
   "depends_on": null,
   "description": null,
   "docstatus": 0,
   "dt": "Task",
   "fetch_from": null,
   "fetch_if_empty": 0,
   "fieldname": "total_expense_claim",
   "fieldtype": "Currency",
   "hidden": 0,
   "hide_border": 0,
   "hide_days": 0,
   "hide_seconds": 0,
   "idx": 35,
   "ignore_user_permissions": 0,
   "ignore_xss_filter": 0,
   "in_global_search": 0,
   "in_list_view": 0,
   "in_preview": 0,
   "in_standard_filter": 0,
   "insert_after": "total_costing_amount",
   "is_system_generated": 1,
   "is_virtual": 0,
   "label": "Total Expense Claim (via Expense Claim)",
   "length": 0,
   "mandatory_depends_on": null,
   "modified": "2024-03-12 13:26:13.823356",
   "modified_by": "Administrator",
   "module": null,
   "name": "Task-total_expense_claim",
   "no_copy": 0,
   "non_negative": 0,
   "options": "Company:company:default_currency",
   "owner": "Administrator",
   "permlevel": 0,
   "precision": "",
   "print_hide": 0,
   "print_hide_if_no_value": 0,
   "print_width": null,
   "read_only": 1,
   "read_only_depends_on": null,
   "report_hide": 0,
   "reqd": 0,
   "search_index": 0,
   "show_dashboard": 0,
   "sort_options": 0,
   "translatable": 0,
   "unique": 0,
   "width": null
  }
 ],
 "custom_perms": [
  {
   "_assign": null,
   "_comments": null,
   "_liked_by": null,
   "_user_tags": null,
   "amend": 0,
   "cancel": 0,
   "create": 1,
   "creation": "2013-01-29 19:25:50",
   "delete": 1,
   "docstatus": 0,
   "email": 1,
   "export": 0,
   "idx": 1,
   "if_owner": 0,
   "import": 0,
   "modified": "2024-03-11 15:35:47.804878",
   "modified_by": "Administrator",
   "name": "77a8e0f30b",
   "owner": "Administrator",
   "parent": "Task",
   "permlevel": 0,
   "print": 1,
   "read": 1,
   "report": 1,
   "role": "Projects User",
   "select": 0,
   "share": 1,
   "submit": 0,
   "write": 1
  },
  {
   "_assign": null,
   "_comments": null,
   "_liked_by": null,
   "_user_tags": null,
   "amend": 0,
   "cancel": 0,
   "create": 0,
   "creation": "2024-03-11 15:35:47.885973",
   "delete": 0,
   "docstatus": 0,
   "email": 0,
   "export": 1,
   "idx": 0,
   "if_owner": 0,
   "import": 0,
   "modified": "2024-03-11 15:35:47.974162",
   "modified_by": "Administrator",
   "name": "562867271c",
   "owner": "Administrator",
   "parent": "Task",
   "permlevel": 0,
   "print": 0,
   "read": 0,
   "report": 0,
   "role": "Employee Self Service",
   "select": 1,
   "share": 0,
   "submit": 0,
   "write": 0
  },
  {
   "_assign": null,
   "_comments": null,
   "_liked_by": null,
   "_user_tags": null,
   "amend": 0,
   "cancel": 0,
   "create": 1,
   "creation": "2024-05-21 13:46:59.632223",
   "delete": 1,
   "docstatus": 0,
   "email": 0,
   "export": 1,
   "idx": 0,
   "if_owner": 0,
   "import": 0,
   "modified": "2024-05-21 13:46:59.632223",
   "modified_by": "Administrator",
   "name": "7b992b327d",
   "owner": "Administrator",
   "parent": "Task",
   "permlevel": 0,
   "print": 0,
   "read": 1,
   "report": 1,
   "role": "Projects Manager",
   "select": 1,
   "share": 0,
   "submit": 0,
   "write": 1
  }
 ],
 "doctype": "Task",
 "links": [],
 "property_setters": [
  {
   "_assign": null,
   "_comments": null,
   "_liked_by": null,
   "_user_tags": null,
   "creation": "2024-10-18 14:51:41.204855",
   "default_value": null,
   "doc_type": "Task",
   "docstatus": 0,
   "doctype_or_field": "DocType",
   "field_name": null,
   "idx": 0,
   "is_system_generated": 0,
   "modified": "2024-10-18 14:51:41.204855",
   "modified_by": "Administrator",
   "module": null,
   "name": "Task-main-field_order",
   "owner": "Administrator",
   "property": "field_order",
   "property_type": "Data",
   "row_name": null,
   "value": "[\"subject\", \"project\", \"custom_program\", \"custom_subservice_area\", \"custom_product\", \"issue\", \"type\", \"color\", \"is_group\", \"is_template\", \"column_break0\", \"status\", \"priority\", \"task_weight\", \"parent_task\", \"completed_by\", \"completed_on\", \"sb_timeline\", \"exp_start_date\", \"expected_time\", \"start\", \"column_break_11\", \"exp_end_date\", \"progress\", \"duration\", \"is_milestone\", \"sb_details\", \"description\", \"sb_depends_on\", \"depends_on\", \"depends_on_tasks\", \"sb_actual\", \"act_start_date\", \"actual_time\", \"column_break_15\", \"act_end_date\", \"sb_costing\", \"total_costing_amount\", \"total_expense_claim\", \"column_break_20\", \"total_billing_amount\", \"sb_more_info\", \"review_date\", \"closing_date\", \"column_break_22\", \"department\", \"company\", \"lft\", \"rgt\", \"old_parent\", \"template_task\"]"
  }
 ],
 "sync_on_migrate": 1
}